 {
  "photos":[
    {
      "id": 1,
      "name": "sunset over Mount Lavinia beach",
      "category": "sunset",
      "src": "https://i.ibb.co/0DP54Th/IMG-20200229-174708-01.jpg",
     "sizes": ["(min-width: 320px) 50vw,(min-width: 1024px) 33.3vw,100vw"],
     "width": 9,
     "height": 16,
      "location": {
        "Country": "Sri lanka",
        "city": "Mount Lavinia",
        "place": "Mount lavinia beach",
        "geo": {
          "lat": "-37.3159",
          "lng": "81.1496"
        }
      }
    },
  
    {
      "id": 2,
      "name": "sunset over Crow Island beach",
      "category": "sunset",
      "src": "https://i.ibb.co/9sTwDPX/dav.jpg",
     "sizes": ["(min-width: 320px) 50vw,(min-width: 1024px) 33.3vw,100vw"],
     "width": 4,
     "height": 3,
      "location": {
        "Country": "Sri lanka",
        "city": "Colombo",
        "place": "Mattakuliya",
        "geo": {
          "lat": "-37.3159",
          "lng": "81.1496"
        }
      }
    },
  
    {
      "id": 3,
      "name": "sunset over Diyatha Uyana",
      "category": "sunset",
      "src": "https://i.ibb.co/J7zgpyy/bty.jpg",
     "sizes": ["(min-width: 320px) 50vw,(min-width: 1024px) 33.3vw,100vw"],
     "width": 4,
     "height": 3,
      "location": {
        "Country": "Sri lanka",
        "city": "Sri Jayawardanapura Kotte",
        "place": "Diyatha Uyana",
        "geo": {
          "lat": "-37.3159",
          "lng": "81.1496"
        }
      }
    },
   
   
   
   {
      "id": 4,
      "name": "sunset over Wellawatte",
      "category": "sunset",
      "src": "https://i.ibb.co/mTT66mz/IMG-20201007-181037-01.jpg",
    "sizes": ["(min-width: 480px) 50vw,(min-width: 1024px) 33.3vw,100vw"],
     "width": 4,
     "height": 3,
      "location": {
        "Country": "Sri lanka",
        "city": "Colombo",
        "place": "Wellawatte Kinross Beach",
        "geo": {
          "lat": "-37.3159",
          "lng": "81.1496"
        }
      }
    },
   
   {
      "id": 5,
      "name": "sunset over Nelum Kulana",
      "category": "sunset",
      "src": "https://i.ibb.co/bXckHZ8/IMG-20200221-174124-01-01.jpg",
    "sizes": ["(min-width: 320px) 50vw,(min-width: 1024px) 33.3vw,100vw"],
     "width": 9,
     "height": 16,
      "location": {
        "Country": "Sri lanka",
        "city": "Colombo",
        "place": "Maradana Railway Station",
        "geo": {
          "lat": "-37.3159",
          "lng": "81.1496"
        }
      }
    }
  
]
  
}

